pyuipc.cp311-win_amd64.pyd
fsuipc/__init__.py
fsuipc/fsuipc.py
fsuipc/prepared_data.py
fsuipc/py.typed
pyuipc-stubs/__init__.pyi
fsuipc-1.5.0.dist-info/LICENSE
fsuipc-1.5.0.dist-info/METADATA
fsuipc-1.5.0.dist-info/WHEEL
fsuipc-1.5.0.dist-info/top_level.txt
fsuipc-1.5.0.dist-info/RECORD
