Metadata-Version: 2.1
Name: fsuipc
Version: 1.5.0
Summary: Client wrapper for FSUIPC
Home-page: https://github.com/tjensen/fsuipc
Author: Tim Jensen
Author-email: tim.l.jensen@gmail.com
License: MIT
Project-URL: Source, https://github.com/tjensen/fsuipc
Project-URL: Tracker, https://github.com/tjensen/fsuipc/issues
Keywords: flight,simulator,pyuipc
Classifier: Development Status :: 5 - Production/Stable
Classifier: Environment :: Console
Classifier: Environment :: Win32 (MS Windows)
Classifier: License :: OSI Approved :: MIT License
Classifier: Operating System :: Microsoft :: Windows
Classifier: Programming Language :: Python :: 3.7
Classifier: Programming Language :: Python :: 3.8
Classifier: Programming Language :: Python :: 3.9
Classifier: Programming Language :: Python :: 3.10
Classifier: Programming Language :: Python :: 3.11
Classifier: Topic :: Games/Entertainment :: Simulation
Requires-Python: >=3.7
License-File: LICENSE
